{
    "titlemain":"Minha Documentação",
    "pages":[
        {
            "id":0,
            "title":"introdução",
             "content":"Sobre a introducao sobre ...",
             "img":[
                { "title":"Imagem1","path" :"/" },
                { "title":"Imagem2","path" :"/" },
                { "title":"Imagem3","path" :"/" }
             ]
        },
        {
            "id":1,
            "title":"Desenvolvimento",
             "content":"Sobre a Desenvolvimento sobre ...",
             "img":[
                { "title":"Imagem1","path" :"/" },
                { "title":"Imagem2","path" :"/" }
             ]
        },
        {
            "id":2,
            "title":"Como instalar",
             "content":"Sobre a introducao sobre ...",
             "img":[
                { "title":"Imagem1","path" :"/" },
                { "title":"Imagem2","path" :"/" },
                { "title":"Imagem2","path" :"/" },
                { "title":"Imagem2","path" :"/" },
                { "title":"Imagem2","path" :"/" },
                { "title":"Imagem3","path" :"/" }
             ]
        },
        {
            "id":3,
            "title":"Como usar",
             "content":"Sobre a introducao sobre ...",
             "img":[
                { "title":"Imagem1","path" :"/" },
                { "title":"Imagem2","path" :"/" },
                { "title":"Imagem2","path" :"/" },
                { "title":"Imagem2","path" :"/" },
                { "title":"Imagem3","path" :"/" }
             ]
        },
        {
            "id":4,
            "title":"Considerações finais",
             "content":"Sobre a introducao sobre ...",
             "img":[]
        },
        {
            "id":5,
            "title":"Autor",
             "content":"Sobre o Autor sobre ...",
             "img":[
                { "title":"Imagem1","path" :"/" },
                { "title":"Imagem2","path" :"/" },
                { "title":"Imagem3","path" :"/" }
             ]
        },
        {
            "id":6,
            "title":"Licença",
             "content":"Sobre a Licença sobre ...",
             "img":[
                { "title":"Imagem1","path" :"/" },
                { "title":"Imagem2","path" :"/" },
                { "title":"Imagem3","path" :"/" }
             ]
        }
    ]
    
}

