{
   "titlemain": "O Titulo",
   "pages": [
      {
         "id": 0,
         "title": "Indice",
         "link":"indice",
         "data_content": {
            "content": [
               {
                  "title": "Imagem1",
                  "description":"",
                  "path": "https://cdn.jsdelivr.net/gh/devicons/devicon/icons/html5/html5-original-wordmark.svg"
               },
               {
                  "title": "Imagem1",
                  "description":"",
                  "path": "https://cdn.jsdelivr.net/gh/devicons/devicon/icons/html5/html5-original-wordmark.svg"
               }
            ]
         }
      },
      {
         "id": 0,
         "title": "como usar",
         "link":"comousar",
         "data_content": {
            "content": [
               {
                  "title": "Primeiro voce liga a televisao .... ",
                  "description":"Some data",
                  "path": "https://cdn.jsdelivr.net/gh/devicons/devicon/icons/html5/html5-original-wordmark.svg"
               },
               {
                  "title": "Segundo voce faça o nome",
                  "description":"some data",
                  "path": "https://cdn.jsdelivr.net/gh/devicons/devicon/icons/html5/html5-original-wordmark.svg"
               }
            ]
         }
      }
   ]
}